regex_utils/__init__.py
regex_utils/nfa.py
regex_utils/nfautils.py
regex_utils/regex.py
regex_utils-0.1.1.dist-info/METADATA
regex_utils-0.1.1.dist-info/WHEEL
regex_utils-0.1.1.dist-info/licenses/LICENSE
regex_utils-0.1.1.dist-info/RECORD
