Metadata-Version: 2.3
Name: regex-utils
Version: 0.1.1
Summary: Utilities for Regular Expressions in Python
Project-URL: Homepage, https://github.com/avalz/regex-utils
Project-URL: Issues, https://github.com/avalz/regex-utils/issues
Author-email: Andrea Valenza <avalenza89@gmail.com>
License-File: LICENSE
Classifier: License :: OSI Approved :: MIT License
Classifier: Operating System :: OS Independent
Classifier: Programming Language :: Python :: 3
Requires-Python: >=3.8
Requires-Dist: graphviz
Requires-Dist: more-itertools
